{
  "name": "高橋悠",
  "slug": "yu-takahashi",
  "generation": "1期生",
  "catch": "小さく試して、事業の芽を育てる",
  "image": "/images/students/yu.jpg",
  "tags": [
    "起業",
    "AI",
    "地域",
    "活動公開"
  ],
  "interests": [
    {
      "theme": "起業",
      "reason": "小さな実験を続けながら、誰かの困りごとにちゃんと届く事業の形を探しています。"
    },
    {
      "theme": "AI",
      "reason": "調査や検証の速度を上げ、アイデアを早く試すための道具としてAIを使っています。"
    },
    {
      "theme": "地域",
      "reason": "地域にある困りごとを、外から押しつけないサービス案に変えることに関心があります。"
    },
    {
      "theme": "活動公開",
      "reason": "検証の過程や学びを残し、事業の芽がどう育っているかを見えるようにしたいです。"
    }
  ],
  "talkTopics": [
    "事業アイデア",
    "ユーザーヒアリング",
    "AI活用",
    "地域ビジネス"
  ],
  "currentQuestion": "学生の小さな実験は、どうすれば続く事業になるのか",
  "currentProject": "地域の困りごとを学生のサービス案に変える検証",
  "projectDetail": "地域の人へのヒアリングから困りごとの輪郭をつかみ、学生でも試せるサービス案と検証計画に落とし込んでいます。",
  "oneOnOneMessage": "事業アイデアの壁打ちや、最初の検証設計を一緒に考えられます。",
  "featured": false,
  "story": "思いついたアイデアを大きく語るだけでなく、誰に聞けばよいか、何を試せばよいかまで落とし込むことに関心があります。地域の中で成立する事業の形を探っています。",
  "about": [
    "高橋悠さんは、事業アイデアを大きく語るだけで終わらせず、誰に聞くのか、何を試すのか、どの仮説から確かめるのかまで落とし込むことに関心があります。AIも調査や検証を速く進めるための道具として使っています。",
    "地域の困りごとをサービス案に変えるときも、外から解決策を押しつけるのではなく、相手の言葉を聞きながら形を探します。小さな実験を続け、事業の芽が育つ条件を確かめている人です。"
  ],
  "questions": [
    "学生の小さな実験は、どうすれば続く事業になるのか",
    "誰かの困りごとを、押しつけではないサービスにするには何が必要か"
  ],
  "canConsult": [
    "事業アイデアの整理",
    "ユーザーヒアリング",
    "検証計画",
    "ピッチの組み立て"
  ],
  "recentActivities": [
    "地域サービス案の検証",
    "ヒアリングシート作成",
    "学生起業の事例調査"
  ],
  "links": {
    "note": "",
    "youtube": "",
    "podcast": "",
    "x": "",
    "instagram": "",
    "contact": "https://forms.gle/xxxx"
  },
  "projectSlug": "local-service"
}